LICENSE
README.md
setup.py
asrl_pyboreas.egg-info/PKG-INFO
asrl_pyboreas.egg-info/SOURCES.txt
asrl_pyboreas.egg-info/dependency_links.txt
asrl_pyboreas.egg-info/requires.txt
asrl_pyboreas.egg-info/top_level.txt
pyboreas/__init__.py
pyboreas/boreas.py
pyboreas/download_task.py
pyboreas/data/__init__.py
pyboreas/data/bounding_boxes.py
pyboreas/data/calib.py
pyboreas/data/pointcloud.py
pyboreas/data/sensors.py
pyboreas/data/sequence.py
pyboreas/data/splits.py
pyboreas/eval/__init__.py
pyboreas/eval/detection.py
pyboreas/eval/interpolate.py
pyboreas/eval/localization.py
pyboreas/eval/odometry.py
pyboreas/eval/odometry_aeva.py
pyboreas/eval/submission_checker.py
pyboreas/test/__init__.py
pyboreas/test/test_localization.py
pyboreas/test/test_odometry.py
pyboreas/utils/__init__.py
pyboreas/utils/lgmath.py
pyboreas/utils/odometry.py
pyboreas/utils/radar.py
pyboreas/utils/utils.py
pyboreas/vis/__init__.py
pyboreas/vis/plot_processed_error.py
pyboreas/vis/vis_utils.py