Metadata-Version: 2.1
Name: asrl-pyboreas
Version: 1.0.5
Summary: A toolkit for working with the Boreas dataset in Python
Home-page: https://github.com/utiasASRL/boreas-devkit
Author: Keenan Burnett, Andrew Li, Shichen Lu, Jingxing Qian, Yuchen Wu, David Yoon
Author-email: boreas@robotics.utias.utoronto.ca
License: BSD
Platform: UNKNOWN
Requires-Python: >=3.8
License-File: LICENSE
